nikocraft/__init__.py
nikocraft/app.py
nikocraft/constants.py
nikocraft/utils/__init__.py
nikocraft/utils/config.py
nikocraft/utils/enum.py
nikocraft/utils/file.py
nikocraft/utils/log.py
nikocraft/utils/time.py
nikocraft/window/__init__.py
nikocraft/window/clock.py
nikocraft/window/debug_screen.py
nikocraft/window/event_hook.py
nikocraft/window/font.py
nikocraft/window/rgb.py
nikocraft/window/scene.py
nikocraft/window/surface_interface.py
nikocraft/window/vector2d.py
nikocraft/window/vector3d.py
nikocraft/window/window.py
nikocraft-0.0.4.dist-info/LICENSE
nikocraft-0.0.4.dist-info/METADATA
nikocraft-0.0.4.dist-info/WHEEL
nikocraft-0.0.4.dist-info/top_level.txt
nikocraft-0.0.4.dist-info/RECORD
